varport/__init__.py
varport/report_generator.py
varport/var_processor.py
varport-0.1.1.dist-info/LICENSE.txt
varport-0.1.1.dist-info/METADATA
varport-0.1.1.dist-info/WHEEL
varport-0.1.1.dist-info/top_level.txt
varport-0.1.1.dist-info/RECORD
