Metadata-Version: 2.1
Name: varport
Version: 0.1.1
Summary: A library to calculate derivatives VAR portfolio and generate a report
Home-page: https://github.com/your-github-account/varport
Author: Your Name
Author-email: raghuramanvarp@gmail.com
Classifier: Programming Language :: Python :: 3
Classifier: License :: OSI Approved :: MIT License
Classifier: Operating System :: OS Independent
Requires-Python: >=3.8
License-File: LICENSE.txt
Requires-Dist: polars (>=0.10)
Requires-Dist: numpy (>=1.21)
Requires-Dist: seaborn (>=0.11)
Requires-Dist: matplotlib (>=3.4)
Requires-Dist: fpdf (>=1.7)
Requires-Dist: scipy (>=1.13.1)
